logzy/__init__.py
logzy/app.py
logzy/convert.py
logzy/transform.py
logzy-0.1.2.dist-info/entry_points.txt
logzy-0.1.2.dist-info/WHEEL
logzy-0.1.2.dist-info/METADATA
logzy-0.1.2.dist-info/RECORD
