Metadata-Version: 2.1
Name: logzy
Version: 0.1.2
Summary: A tool for converting f-strings in log functions to lazy-logging
Author: Alex Harford
Author-email: harford@gmail.com
Requires-Python: >=3.10,<4.0
Classifier: Programming Language :: Python :: 3
Classifier: Programming Language :: Python :: 3.10
Requires-Dist: astroid (>=2.12.12,<3.0.0)
Requires-Dist: libcst (>=0.4.7,<0.5.0)
